{
  "name": "Hattrem",
  "national": "0857",
  "forms": [
    {
      "name": "Standard",
      "species": "Serene Pokémon",
      "height": {
        "metric": 0.6,
        "imperial": 24
      },
      "weight": {
        "metric": 4.8,
        "imperial": 10.6
      },
      "ability": {
        "normal": [
          "Healer",
          "Anticipation"
        ],
        "hidden": "Magic Bounce"
      },
      "stats": {
        "hp": 57,
        "atk": 40,
        "def": 65,
        "satk": 86,
        "sdef": 73,
        "spd": 49
      },
      "moves": [
        [
          "evo",
          "Brutal Swing"
        ],
        [
          null,
          "Confusion"
        ],
        [
          null,
          "Disarming Voice"
        ],
        [
          null,
          "Play Nice"
        ],
        [
          null,
          "Life Dew"
        ],
        [
          15,
          "Aromatic Mist"
        ],
        [
          20,
          "Psybeam"
        ],
        [
          25,
          "Heal Pulse"
        ],
        [
          30,
          "Dazzling Gleam"
        ],
        [
          37,
          "Calm Mind"
        ],
        [
          44,
          "Psychic"
        ],
        [
          51,
          "Healing Wish"
        ],
        [
          "TM002",
          "Charm"
        ],
        [
          "TM007",
          "Protect"
        ],
        [
          "TM016",
          "Psybeam"
        ],
        [
          "TM019",
          "Disarming Voice"
        ],
        [
          "TM025",
          "Facade"
        ],
        [
          "TM032",
          "Swift"
        ],
        [
          "TM033",
          "Magical Leaf"
        ],
        [
          "TM037",
          "Draining Kiss"
        ],
        [
          "TM041",
          "Stored Power"
        ],
        [
          "TM047",
          "Endure"
        ],
        [
          "TM054",
          "Psyshock"
        ],
        [
          "TM070",
          "Sleep Talk"
        ],
        [
          "TM074",
          "Reflect"
        ],
        [
          "TM075",
          "Light Screen"
        ],
        [
          "TM079",
          "Dazzling Gleam"
        ],
        [
          "TM080",
          "Metronome"
        ],
        [
          "TM082",
          "Thunder Wave"
        ],
        [
          "TM085",
          "Rest"
        ],
        [
          "TM092",
          "Imprison"
        ],
        [
          "TM094",
          "Dark Pulse"
        ],
        [
          "TM098",
          "Skill Swap"
        ],
        [
          "TM103",
          "Substitute"
        ],
        [
          "TM109",
          "Trick"
        ],
        [
          "TM111",
          "Giga Drain"
        ],
        [
          "TM120",
          "Psychic"
        ],
        [
          "TM127",
          "Play Rough"
        ],
        [
          "TM129",
          "Calm Mind"
        ],
        [
          "TM130",
          "Helping Hand"
        ],
        [
          "TM132",
          "Baton Pass"
        ],
        [
          "TM138",
          "Psychic Terrain"
        ],
        [
          "TM139",
          "Misty Terrain"
        ],
        [
          "TM161",
          "Trick Room"
        ],
        [
          "TM171",
          "Tera Blast"
        ],
        [
          "TM203",
          "Psych Up"
        ],
        [
          "TM217",
          "Future Sight"
        ],
        [
          "TM218",
          "Expanding Force"
        ],
        [
          "egg",
          "After You"
        ],
        [
          "egg",
          "Quash"
        ],
        [
          "egg",
          "Mystical Fire"
        ],
        [
          "egg",
          "Nuzzle"
        ]
      ]
    }
  ]
}