{
  "name": "Meowth",
  "national": "0052",
  "forms": [
    {
      "name": "Standard",
      "species": "Scratch Cat Pokémon",
      "height": {
        "metric": 0.4,
        "imperial": 16
      },
      "weight": {
        "metric": 4.2,
        "imperial": 9.3
      },
      "ability": {
        "normal": [
          "Pickup",
          "Technician"
        ],
        "hidden": "Unnerve"
      },
      "stats": {
        "hp": 40,
        "atk": 45,
        "def": 35,
        "satk": 40,
        "sdef": 40,
        "spd": 90
      },
      "types": [
        "normal"
      ],
      "moves": [
        [
          null,
          "Growl"
        ],
        [
          null,
          "Fake Out"
        ],
        [
          4,
          "Feint"
        ],
        [
          8,
          "Scratch"
        ],
        [
          12,
          "Pay Day"
        ],
        [
          16,
          "Bite"
        ],
        [
          20,
          "Taunt"
        ],
        [
          24,
          "Assurance"
        ],
        [
          29,
          "Fury Swipes"
        ],
        [
          32,
          "Screech"
        ],
        [
          36,
          "Slash"
        ],
        [
          40,
          "Nasty Plot"
        ],
        [
          44,
          "Play Rough"
        ],
        [
          "TM001",
          "Take Down"
        ],
        [
          "TM002",
          "Charm"
        ],
        [
          "TM003",
          "Fake Tears"
        ],
        [
          "TM004",
          "Agility"
        ],
        [
          "TM007",
          "Protect"
        ],
        [
          "TM018",
          "Thief"
        ],
        [
          "TM020",
          "Trailblaze"
        ],
        [
          "TM022",
          "Chilling Water"
        ],
        [
          "TM025",
          "Facade"
        ],
        [
          "TM027",
          "Aerial Ace"
        ],
        [
          "TM030",
          "Snarl"
        ],
        [
          "TM031",
          "Metal Claw"
        ],
        [
          "TM032",
          "Swift"
        ],
        [
          "TM034",
          "Icy Wind"
        ],
        [
          "TM047",
          "Endure"
        ],
        [
          "TM049",
          "Sunny Day"
        ],
        [
          "TM050",
          "Rain Dance"
        ],
        [
          "TM055",
          "Dig"
        ],
        [
          "TM057",
          "False Swipe"
        ],
        [
          "TM060",
          "U-turn"
        ],
        [
          "TM061",
          "Shadow Claw"
        ],
        [
          "TM062",
          "Foul Play"
        ],
        [
          "TM066",
          "Body Slam"
        ],
        [
          "TM070",
          "Sleep Talk"
        ],
        [
          "TM071",
          "Seed Bomb"
        ],
        [
          "TM082",
          "Thunder Wave"
        ],
        [
          "TM085",
          "Rest"
        ],
        [
          "TM087",
          "Taunt"
        ],
        [
          "TM094",
          "Dark Pulse"
        ],
        [
          "TM101",
          "Power Gem"
        ],
        [
          "TM102",
          "Gunk Shot"
        ],
        [
          "TM103",
          "Substitute"
        ],
        [
          "TM114",
          "Shadow Ball"
        ],
        [
          "TM117",
          "Hyper Voice"
        ],
        [
          "TM126",
          "Thunderbolt"
        ],
        [
          "TM127",
          "Play Rough"
        ],
        [
          "TM128",
          "Amnesia"
        ],
        [
          "TM130",
          "Helping Hand"
        ],
        [
          "TM140",
          "Nasty Plot"
        ],
        [
          "TM166",
          "Thunder"
        ],
        [
          "TM171",
          "Tera Blast"
        ],
        [
          "TM177",
          "Spite"
        ],
        [
          "TM181",
          "Knock Off"
        ],
        [
          "TM199",
          "Lash Out"
        ],
        [
          "TM202",
          "Pain Split"
        ],
        [
          "TM203",
          "Psych Up"
        ],
        [
          "TM204",
          "Double-Edge"
        ],
        [
          "TM205",
          "Endeavor"
        ],
        [
          "TM221",
          "Throat Chop"
        ],
        [
          "egg",
          "Tail Whip"
        ],
        [
          "egg",
          "Hypnosis"
        ],
        [
          "egg",
          "Flail"
        ],
        [
          "egg",
          "Spite"
        ],
        [
          "egg",
          "Covet"
        ],
        [
          "egg",
          "Last Resort"
        ]
      ]
    },
    {
      "name": "Alolan",
      "species": "Scratch Cat Pokémon",
      "height": {
        "metric": 0.4,
        "imperial": 16
      },
      "weight": {
        "metric": 4.2,
        "imperial": 9.3
      },
      "ability": {
        "normal": [
          "Pickup",
          "Technician"
        ],
        "hidden": "Rattled"
      },
      "stats": {
        "hp": 40,
        "atk": 35,
        "def": 35,
        "satk": 50,
        "sdef": 40,
        "spd": 90
      },
      "types": [
        "dark"
      ],
      "moves": [
        [
          null,
          "Growl"
        ],
        [
          null,
          "Fake Out"
        ],
        [
          4,
          "Feint"
        ],
        [
          8,
          "Scratch"
        ],
        [
          12,
          "Pay Day"
        ],
        [
          16,
          "Bite"
        ],
        [
          20,
          "Taunt"
        ],
        [
          24,
          "Assurance"
        ],
        [
          29,
          "Fury Swipes"
        ],
        [
          32,
          "Screech"
        ],
        [
          36,
          "Night Slash"
        ],
        [
          40,
          "Nasty Plot"
        ],
        [
          44,
          "Play Rough"
        ],
        [
          "TM001",
          "Take Down"
        ],
        [
          "TM002",
          "Charm"
        ],
        [
          "TM003",
          "Fake Tears"
        ],
        [
          "TM004",
          "Agility"
        ],
        [
          "TM007",
          "Protect"
        ],
        [
          "TM017",
          "Confuse Ray"
        ],
        [
          "TM018",
          "Thief"
        ],
        [
          "TM020",
          "Trailblaze"
        ],
        [
          "TM022",
          "Chilling Water"
        ],
        [
          "TM025",
          "Facade"
        ],
        [
          "TM027",
          "Aerial Ace"
        ],
        [
          "TM030",
          "Snarl"
        ],
        [
          "TM031",
          "Metal Claw"
        ],
        [
          "TM032",
          "Swift"
        ],
        [
          "TM034",
          "Icy Wind"
        ],
        [
          "TM047",
          "Endure"
        ],
        [
          "TM049",
          "Sunny Day"
        ],
        [
          "TM050",
          "Rain Dance"
        ],
        [
          "TM055",
          "Dig"
        ],
        [
          "TM060",
          "U-turn"
        ],
        [
          "TM061",
          "Shadow Claw"
        ],
        [
          "TM062",
          "Foul Play"
        ],
        [
          "TM066",
          "Body Slam"
        ],
        [
          "TM070",
          "Sleep Talk"
        ],
        [
          "TM071",
          "Seed Bomb"
        ],
        [
          "TM082",
          "Thunder Wave"
        ],
        [
          "TM085",
          "Rest"
        ],
        [
          "TM087",
          "Taunt"
        ],
        [
          "TM094",
          "Dark Pulse"
        ],
        [
          "TM101",
          "Power Gem"
        ],
        [
          "TM102",
          "Gunk Shot"
        ],
        [
          "TM103",
          "Substitute"
        ],
        [
          "TM114",
          "Shadow Ball"
        ],
        [
          "TM117",
          "Hyper Voice"
        ],
        [
          "TM126",
          "Thunderbolt"
        ],
        [
          "TM127",
          "Play Rough"
        ],
        [
          "TM128",
          "Amnesia"
        ],
        [
          "TM130",
          "Helping Hand"
        ],
        [
          "TM140",
          "Nasty Plot"
        ],
        [
          "TM166",
          "Thunder"
        ],
        [
          "TM171",
          "Tera Blast"
        ],
        [
          "TM177",
          "Spite"
        ],
        [
          "TM181",
          "Knock Off"
        ],
        [
          "TM199",
          "Lash Out"
        ],
        [
          "TM203",
          "Psych Up"
        ],
        [
          "TM204",
          "Double-Edge"
        ],
        [
          "TM205",
          "Endeavor"
        ],
        [
          "TM221",
          "Throat Chop"
        ],
        [
          "TM224",
          "Curse"
        ],
        [
          "egg",
          "Hypnosis"
        ],
        [
          "egg",
          "Flail"
        ],
        [
          "egg",
          "Spite"
        ],
        [
          "egg",
          "Covet"
        ],
        [
          "egg",
          "Flatter"
        ],
        [
          "egg",
          "Parting Shot"
        ]
      ]
    },
    {
      "name": "Galarian",
      "species": "Scratch Cat Pokémon",
      "height": {
        "metric": 0.4,
        "imperial": 16
      },
      "weight": {
        "metric": 7.5,
        "imperial": 16.5
      },
      "ability": {
        "normal": [
          "Pickup",
          "Tough Claws"
        ],
        "hidden": "Unnerve"
      },
      "stats": {
        "hp": 50,
        "atk": 65,
        "def": 55,
        "satk": 40,
        "sdef": 40,
        "spd": 40
      },
      "types": [
        "steel"
      ],
      "moves": [
        [
          null,
          "Growl"
        ],
        [
          null,
          "Fake Out"
        ],
        [
          4,
          "Hone Claws"
        ],
        [
          8,
          "Scratch"
        ],
        [
          12,
          "Pay Day"
        ],
        [
          16,
          "Metal Claw"
        ],
        [
          20,
          "Taunt"
        ],
        [
          24,
          "Swagger"
        ],
        [
          29,
          "Fury Swipes"
        ],
        [
          32,
          "Screech"
        ],
        [
          36,
          "Slash"
        ],
        [
          40,
          "Metal Sound"
        ],
        [
          44,
          "Thrash"
        ],
        [
          "TM001",
          "Take Down"
        ],
        [
          "TM002",
          "Charm"
        ],
        [
          "TM003",
          "Fake Tears"
        ],
        [
          "TM007",
          "Protect"
        ],
        [
          "TM018",
          "Thief"
        ],
        [
          "TM020",
          "Trailblaze"
        ],
        [
          "TM025",
          "Facade"
        ],
        [
          "TM027",
          "Aerial Ace"
        ],
        [
          "TM031",
          "Metal Claw"
        ],
        [
          "TM043",
          "Fling"
        ],
        [
          "TM047",
          "Endure"
        ],
        [
          "TM049",
          "Sunny Day"
        ],
        [
          "TM050",
          "Rain Dance"
        ],
        [
          "TM055",
          "Dig"
        ],
        [
          "TM057",
          "False Swipe"
        ],
        [
          "TM058",
          "Brick Break"
        ],
        [
          "TM060",
          "U-turn"
        ],
        [
          "TM061",
          "Shadow Claw"
        ],
        [
          "TM062",
          "Foul Play"
        ],
        [
          "TM066",
          "Body Slam"
        ],
        [
          "TM070",
          "Sleep Talk"
        ],
        [
          "TM071",
          "Seed Bomb"
        ],
        [
          "TM080",
          "Metronome"
        ],
        [
          "TM085",
          "Rest"
        ],
        [
          "TM087",
          "Taunt"
        ],
        [
          "TM088",
          "Swords Dance"
        ],
        [
          "TM093",
          "Flash Cannon"
        ],
        [
          "TM094",
          "Dark Pulse"
        ],
        [
          "TM099",
          "Iron Head"
        ],
        [
          "TM102",
          "Gunk Shot"
        ],
        [
          "TM103",
          "Substitute"
        ],
        [
          "TM104",
          "Iron Defense"
        ],
        [
          "TM105",
          "X-Scissor"
        ],
        [
          "TM108",
          "Crunch"
        ],
        [
          "TM114",
          "Shadow Ball"
        ],
        [
          "TM116",
          "Stealth Rock"
        ],
        [
          "TM117",
          "Hyper Voice"
        ],
        [
          "TM126",
          "Thunderbolt"
        ],
        [
          "TM127",
          "Play Rough"
        ],
        [
          "TM128",
          "Amnesia"
        ],
        [
          "TM130",
          "Helping Hand"
        ],
        [
          "TM140",
          "Nasty Plot"
        ],
        [
          "TM166",
          "Thunder"
        ],
        [
          "TM170",
          "Steel Beam"
        ],
        [
          "TM171",
          "Tera Blast"
        ],
        [
          "TM177",
          "Spite"
        ],
        [
          "TM180",
          "Gyro Ball"
        ],
        [
          "TM181",
          "Knock Off"
        ],
        [
          "TM199",
          "Lash Out"
        ],
        [
          "TM204",
          "Double-Edge"
        ],
        [
          "TM205",
          "Endeavor"
        ],
        [
          "TM221",
          "Throat Chop"
        ],
        [
          "TM223",
          "Metal Sound"
        ],
        [
          "TM224",
          "Curse"
        ],
        [
          "egg",
          "Flail"
        ],
        [
          "egg",
          "Spite"
        ],
        [
          "egg",
          "Covet"
        ],
        [
          "egg",
          "Double-Edge"
        ],
        [
          "egg",
          "Curse"
        ],
        [
          "egg",
          "Night Slash"
        ]
      ]
    }
  ]
}